iqm/cortex_cli/__init__.py
iqm/cortex_cli/auth.py
iqm/cortex_cli/cortex_cli.py
iqm/cortex_cli/models.py
iqm/cortex_cli/py.typed
iqm/cortex_cli/token_manager.py
iqm_cortex_cli-6.1.dist-info/licenses/AUTHORS.rst
iqm_cortex_cli-6.1.dist-info/licenses/LICENSE.rst
iqm_cortex_cli-6.1.dist-info/METADATA
iqm_cortex_cli-6.1.dist-info/WHEEL
iqm_cortex_cli-6.1.dist-info/entry_points.txt
iqm_cortex_cli-6.1.dist-info/top_level.txt
iqm_cortex_cli-6.1.dist-info/RECORD
