Metadata-Version: 2.4
Name: iqm-cortex-cli
Version: 6.1
Summary: CLI for managing user authentication when using IQM quantum computers
Author-email: IQM Finland Oy <developers@meetiqm.com>
License:                                  Apache License
Project-URL: homepage, https://github.com/iqm-finland/cortex-cli
Project-URL: documentation, https://iqm-finland.github.io/cortex-cli
Project-URL: repository, https://github.com/iqm-finland/cortex-cli.git
Project-URL: changelog, https://github.com/iqm-finland/cortex-cli/blob/main/CHANGELOG.rst
Classifier: Development Status :: 4 - Beta
Classifier: Programming Language :: Python :: 3 :: Only
Classifier: Topic :: Scientific/Engineering :: Physics
Classifier: Intended Audience :: Science/Research
Classifier: License :: OSI Approved :: Apache Software License
Requires-Python: <3.12,>=3.9
License-File: LICENSE.rst
License-File: AUTHORS.rst
Requires-Dist: click<9,>=8.1.6
Requires-Dist: jsonschema>=4.6.0
Requires-Dist: psutil>=5.9.2
Requires-Dist: pydantic<3.0,>=2.4.2
Requires-Dist: python-daemon>=2.3.0
Requires-Dist: requests>=2.26.0
Provides-Extra: dev
Requires-Dist: tox==4.11.4; extra == "dev"
Provides-Extra: testing
Requires-Dist: black==23.12.0; extra == "testing"
Requires-Dist: isort==5.13.2; extra == "testing"
Requires-Dist: mypy==1.7.1; extra == "testing"
Requires-Dist: pytest==7.4.3; extra == "testing"
Requires-Dist: pytest-cov==4.1.0; extra == "testing"
Requires-Dist: pytest-pylint==0.21.0; extra == "testing"
Requires-Dist: mockito==1.4.0; extra == "testing"
Requires-Dist: types-requests==2.28.9; extra == "testing"
Provides-Extra: docs
Requires-Dist: sphinx==7.2.6; extra == "docs"
Requires-Dist: sphinx-book-theme==1.1.2; extra == "docs"
Dynamic: license-file
